setup.py
DataGravity/__init__.py
DataGravity.egg-info/PKG-INFO
DataGravity.egg-info/SOURCES.txt
DataGravity.egg-info/dependency_links.txt
DataGravity.egg-info/not-zip-safe
DataGravity.egg-info/top_level.txt