Metadata-Version: 1.0
Name: DataGravity
Version: 0.1
Summary: DataGravity Discovery Series Library
Home-page: https://github.com/datagravityinc/DataGravity
Author: Andrew Hay
Author-email: ahay@datagravity.com
License: MIT
Platform: UNKNOWN
